once_webscraper/__init__.py
once_webscraper/belli.py
once_webscraper-0.3.5.dist-info/METADATA
once_webscraper-0.3.5.dist-info/WHEEL
once_webscraper-0.3.5.dist-info/top_level.txt
once_webscraper-0.3.5.dist-info/RECORD
