Metadata-Version: 2.2
Name: once-webscraper
Version: 0.3.5
Summary: Uma biblioteca simples para web scraping de fornecedores
Home-page: https://github.com/nyronous/once-webscraper
Author: Nyronous
Classifier: Programming Language :: Python :: 3
Classifier: License :: OSI Approved :: MIT License
Classifier: Operating System :: OS Independent
Requires-Python: >=3.6
Requires-Dist: beautifulsoup4>=4.9.3
Requires-Dist: requests>=2.25.1
Requires-Dist: lxml>=4.9.0
Requires-Dist: urllib3>=1.26.0
Requires-Dist: certifi>=2021.10.8
Requires-Dist: charset-normalizer>=2.0.0
Requires-Dist: idna>=3.3
Requires-Dist: soupsieve>=2.3.1
Dynamic: author
Dynamic: classifier
Dynamic: description
Dynamic: description-content-type
Dynamic: home-page
Dynamic: requires-dist
Dynamic: requires-python
Dynamic: summary
